mipack/__init__.py
mipack/utils/__init__.py
mipack/utils/path_utils.py
tests/__init__.py
mipack-0.0.6.dist-info/LICENSE
mipack-0.0.6.dist-info/METADATA
mipack-0.0.6.dist-info/WHEEL
mipack-0.0.6.dist-info/top_level.txt
mipack-0.0.6.dist-info/RECORD
